Workbook
Name NativeTimeline_Date: #N/A
Name Slicer_Region: #N/A

Sheet Project Instructions
A1: PR. Final Project - "Data Intelligence Dashboard"
A2: Dataset: Use the 'Final Project Dataset' sheet containing 200+ records of customer transactions. Objective: Create a full-fledged analysis and reporting solution using Excel to analyze customer transactions, find insights, and build visualizations and dashboards. Key Topics to Implement: - Date & Time Functions: TODAY, NOW, DATEDIF, EOMONTH - FILTER Function for multi-value returns - Conditional Formatting with Icons/Arrows - Create Timestamp (using NOW and iterative calculations) - WHAT-IF Analysis: Scenario Manager, Goal Seek - Linear Regression using Data Analysis Toolpak - Data Analysis & Storytelling from the dataset - Use GroupBy concepts to find High-Value Customers using formulas - Create Dashboard using: - Pivot Tables - Pivot Charts (Bar, Line, Pie) - Slicers and Timelines - KPI Indicators with Conditional Formatting - Find most frequently purchased product or repeating names using formulas - Compare two lists and extract matching names in a new column - Create Abbreviations using TEXT functions - Build a final report with insights and storytelling Deliverable: - Well-structured workbook with multiple sheets (Raw Data, Analysis, Visualizations, Dashboard) - Summary Insights with key metrics: Total Revenue, Top Customers, Most Sold Products, Regional Sales - Use of all required formulas and functions as listed above

Sheet Dashboard
D7: Total Revenue | G7: Best Region | J7: Most sold Product | M7: Top Customers
D8: =Visaulization!$B$9 -> 229192.47 | G8: =Visaulization!A4 -> East | H8: =GETPIVOTDATA("Total_Amount",Visaulization!$A$3,"Region","East") -> 59288.39 | J8: =Visaulization!J23 -> Bookshelf | K8: =GETPIVOTDATA("Quantity",Visaulization!$J$22,"Product_Name","Bookshelf") -> 35 | M8: =analysis!P3 -> Mark Carter | N8: =GETPIVOTDATA("Total_Amount",analysis!$P$2,"Customer_Name","Mark Carter") -> 15659.65

Sheet Final Project Dataset
N1: Conditional formatting | T1: Abbreviations | V1: scenario summary
A2: Transaction_ID | B2: Date | C2: Customer_ID | D2: Customer_Name | E2: Product_ID | F2: Product_Name | G2: Category | H2: Quantity | I2: Unit_Price | J2: Payment_Method | K2: Region | L2: Customer_Segment | M2: Customer_Since | N2: Total_sales | P2: Today | Q2: Now | R2: Datediff | S2: EOMONTH | T2: Extraction | V2: quantity | W2: price | X2: total amount
A3: TRX0155 | B3: 45393 | C3: CUST023 | D3: Paul Baker | E3: P009 | F3: Monitor | G3: Electronics | H3: 3 | I3: 249.99 | J3: Cash | K3: Central | L3: Basic | M3: 44425 | N3: 749.97 | P3: =TODAY() -> 46172 | Q3: =NOW() -> 46172.696 | R3: =DATEDIF(M3,TODAY(),"D") -> 1747 | S3: =EOMONTH(B3,0) -> 45412 | T3: =LEFT(K3,3) -> Cen | V3: 4 | W3: 350 | X3: =V3*W3 -> 1400
A4: TRX0023 | B4: 45396 | C4: CUST013 | D4: Joseph Jackson | E4: P009 | F4: Monitor | G4: Electronics | H4: 3 | I4: 249.99 | J4: Credit Card | K4: Central | L4: Premium | M4: 44575 | N4: 749.97 | R4: =DATEDIF(M4,TODAY(),"D") -> 1597 | S4: =EOMONTH(B4,0) -> 45412 | T4: =LEFT(K4,3) -> Cen
A5: TRX0139 | B5: 45399 | C5: CUST021 | D5: Kevin Scott | E5: P005 | F5: Blender | G5: Appliances | H5: 3 | I5: 59.99 | J5: PayPal | K5: South | L5: Standard | M5: 45262 | N5: 179.97 | R5: =DATEDIF(M5,TODAY(),"D") -> 910 | S5: =EOMONTH(B5,0) -> 45412 | T5: =LEFT(K5,3) -> Sou
A6: TRX0043 | B6: 45400 | C6: CUST046 | D6: Kathleen Bennett | E6: P005 | F6: Blender | G6: Appliances | H6: 3 | I6: 59.99 | J6: Cash | K6: North | L6: Premium | M6: 45114 | N6: 179.97 | R6: =DATEDIF(M6,TODAY(),"D") -> 1058 | S6: =EOMONTH(B6,0) -> 45412 | T6: =LEFT(K6,3) -> Nor
A7: TRX0212 | B7: 45400 | C7: CUST003 | D7: Michael Brown | E7: P008 | F7: Bookshelf | G7: Furniture | H7: 5 | I7: 149.99 | J7: Credit Card | K7: North | L7: Premium | M7: 45295 | N7: 749.95 | R7: =DATEDIF(M7,TODAY(),"D") -> 877 | S7: =EOMONTH(B7,0) -> 45412 | T7: =LEFT(K7,3) -> Nor
A8: TRX0092 | B8: 45403 | C8: CUST024 | D8: Dorothy Nelson | E8: P005 | F8: Blender | G8: Appliances | H8: 2 | I8: 59.99 | J8: Cash | K8: West | L8: Standard | M8: 44746 | N8: 119.98 | R8: =DATEDIF(M8,TODAY(),"D") -> 1426 | S8: =EOMONTH(B8,0) -> 45412 | T8: =LEFT(K8,3) -> Wes
A9: TRX0193 | B9: 45403 | C9: CUST024 | D9: Dorothy Nelson | E9: P003 | F9: Headphones | G9: Electronics | H9: 5 | I9: 149.99 | J9: Credit Card | K9: Central | L9: Standard | M9: 44418 | N9: 749.95 | R9: =DATEDIF(M9,TODAY(),"D") -> 1754 | S9: =EOMONTH(B9,0) -> 45412 | T9: =LEFT(K9,3) -> Cen
A10: TRX0240 | B10: 45403 | C10: CUST017 | D10: Charles Allen | E10: P005 | F10: Blender | G10: Appliances | H10: 3 | I10: 59.99 | J10: Debit Card | K10: South | L10: Basic | M10: 45007 | N10: 179.97 | R10: =DATEDIF(M10,TODAY(),"D") -> 1165 | S10: =EOMONTH(B10,0) -> 45412 | T10: =LEFT(K10,3) -> Sou
A11: TRX0135 | B11: 45405 | C11: CUST009 | D11: Robert Thomas | E11: P001 | F11: Laptop | G11: Electronics | H11: 3 | I11: 899.99 | J11: PayPal | K11: East | L11: Standard | M11: 45299 | N11: 2699.97 | R11: =DATEDIF(M11,TODAY(),"D") -> 873 | S11: =EOMONTH(B11,0) -> 45412 | T11: =LEFT(K11,3) -> Eas
A12: TRX0185 | B12: 45408 | C12: CUST026 | D12: Karen Hill | E12: P005 | F12: Blender | G12: Appliances | H12: 3 | I12: 59.99 | J12: Cash | K12: West | L12: Premium | M12: 45207 | N12: 179.97 | R12: =DATEDIF(M12,TODAY(),"D") -> 965 | S12: =EOMONTH(B12,0) -> 45412 | T12: =LEFT(K12,3) -> Wes
A13: TRX0138 | B13: 45408 | C13: CUST022 | D13: Susan Green | E13: P008 | F13: Bookshelf | G13: Furniture | H13: 1 | I13: 149.99 | J13: Credit Card | K13: West | L13: Standard | M13: 45103 | N13: 149.99 | R13: =DATEDIF(M13,TODAY(),"D") -> 1069 | S13: =EOMONTH(B13,0) -> 45412 | T13: =LEFT(K13,3) -> Wes
A14: TRX0209 | B14: 45408 | C14: CUST046 | D14: Kathleen Bennett | E14: P008 | F14: Bookshelf | G14: Furniture | H14: 5 | I14: 149.99 | J14: Debit Card | K14: North | L14: Basic | M14: 44830 | N14: 749.95 | R14: =DATEDIF(M14,TODAY(),"D") -> 1342 | S14: =EOMONTH(B14,0) -> 45412 | T14: =LEFT(K14,3) -> Nor
A15: TRX0246 | B15: 45408 | C15: CUST041 | D15: Peter Richardson | E15: P008 | F15: Bookshelf | G15: Furniture | H15: 3 | I15: 149.99 | J15: Cash | K15: North | L15: Premium | M15: 44806 | N15: 449.97 | R15: =DATEDIF(M15,TODAY(),"D") -> 1366 | S15: =EOMONTH(B15,0) -> 45412 | T15: =LEFT(K15,3) -> Nor
... A252: TRX0064 | B252: 45758 | C252: CUST031 | D252: Steven Turner | E252: P010 | F252: Keyboard | G252: Electronics | H252: 3 | I252: 89.99 | J252: Debit Card | K252: North | L252: Premium | M252: 44878 | N252: 269.97 | R252: =DATEDIF(M252,TODAY(),"D") -> 1294 | S252: =EOMONTH(B252,0) -> 45777 | T252: =LEFT(K252,3) -> Nor

Sheet Linear Regression
A1: SUMMARY OUTPUT
A3: Regression Statistics
A4: Multiple R | B4: 0.45809869
A5: R Square | B5: 0.20985441
A6: Adjusted R Square | B6: 0.20665544
A7: Standard Error | B7: 921.40854
A8: Observations | B8: 249
A10: ANOVA
B11: df | C11: SS | D11: MS | E11: F | F11: Significance F
A12: Regression | B12: 1 | C12: 55694513 | D12: 55694513 | E12: 65.60062 | F12: 2.5391277e-14
A13: Residual | B13: 247 | C13: 2.0970144e+08 | D13: 848993.7
A14: Total | B14: 248 | C14: 2.6539596e+08
B16: Coefficients | C16: Standard Error | D16: t Stat | E16: P-value | F16: Lower 95% | G16: Upper 95% | H16: Lower 95.0% | I16: Upper 95.0%
A17: Intercept | B17: -148.18856 | C17: 143.94399 | D17: -1.0294877 | E17: 0.30425761 | F17: -431.70277 | G17: 135.32564 | H17: -431.70277 | I17: 135.32564
A18: 3 | B18: 353.7886 | C18: 43.680728 | D18: 8.0994209 | E18: 2.5391277e-14 | F18: 267.7544 | G18: 439.82281 | H18: 267.7544 | I18: 439.82281

Sheet analysis
A1: FILTER | P1: GROUP BY | R1: Frequently purchased product | T1: Two list and Extract Matching
A2: {=_xlfn._xlws.FILTER('Final Project Dataset'!A2:N252,'Final Project Dataset'!K2:K252="West")} -> TRX0092 | B2: 45403 | C2: CUST024 | D2: Dorothy Nelson | E2: P005 | F2: Blender | G2: Appliances | H2: 2 | I2: 59.99 | J2: Cash | K2: West | L2: Standard | M2: 44746 | N2: 119.98 | P2: Customer Name | Q2: Sum of Total_Amount | R2: Row Labels | S2: Count of Quantity | T2: List A | U2: List B | V2: Matching Names
A3: TRX0185 | B3: 45408 | C3: CUST026 | D3: Karen Hill | E3: P005 | F3: Blender | G3: Appliances | H3: 3 | I3: 59.99 | J3: Cash | K3: West | L3: Premium | M3: 45207 | N3: 179.97 | P3: Mark Carter | Q3: 15659.65 | R3: Bookshelf | S3: 35 | T3: John | U3: Alice | V3: =IF(COUNTIF($T$3:$T$7,U3)>0,"Match","No Match") -> Match
A4: TRX0138 | B4: 45408 | C4: CUST022 | D4: Susan Green | E4: P008 | F4: Bookshelf | G4: Furniture | H4: 1 | I4: 149.99 | J4: Credit Card | K4: West | L4: Standard | M4: 45103 | N4: 149.99 | P4: Edward Mitchell | Q4: 11919.77 | R4: Keyboard | S4: 34 | T4: Emma | U4: John | V4: =IF(COUNTIF($T$3:$T$7,U4)>0,"Match","No Match") -> Match
A5: TRX0191 | B5: 45409 | C5: CUST038 | D5: Michelle Rogers | E5: P002 | F5: Smartphone | G5: Electronics | H5: 3 | I5: 699.99 | J5: Credit Card | K5: West | L5: Basic | M5: 44577 | N5: 2099.97 | P5: Barbara Young | Q5: 10649.8 | R5: Smartphone | S5: 31 | T5: David | U5: Mark | V5: =IF(COUNTIF($T$3:$T$7,U5)>0,"Match","No Match") -> No Match
A6: TRX0122 | B6: 45410 | C6: CUST025 | D6: Mark Carter | E6: P001 | F6: Laptop | G6: Electronics | H6: 4 | I6: 899.99 | J6: Credit Card | K6: West | L6: Standard | M6: 45327 | N6: 3599.96 | P6: Patricia Moore | Q6: 9799.73 | R6: Blender | S6: 29 | T6: Alice | U6: Sam | V6: =IF(COUNTIF($T$3:$T$7,U6)>0,"Match","No Match") -> No Match
A7: TRX0231 | B7: 45412 | C7: CUST018 | D7: Barbara Young | E7: P002 | F7: Smartphone | G7: Electronics | H7: 5 | I7: 699.99 | J7: Cash | K7: West | L7: Basic | M7: 45167 | N7: 3499.95 | P7: Paul Baker | Q7: 8309.74 | R7: Desk | S7: 26 | T7: Christ | U7: Emma | V7: =IF(COUNTIF($T$3:$T$7,U7)>0,"Match","No Match") -> Match
A8: TRX0242 | B8: 45416 | C8: CUST025 | D8: Mark Carter | E8: P007 | F8: Desk | G8: Furniture | H8: 4 | I8: 299.99 | J8: Cash | K8: West | L8: Premium | M8: 44716 | N8: 1199.96 | P8: Dorothy Nelson | Q8: 8269.79 | R8: Monitor | S8: 26
A9: TRX0071 | B9: 45422 | C9: CUST036 | D9: Nancy Collins | E9: P009 | F9: Monitor | G9: Electronics | H9: 5 | I9: 249.99 | J9: Credit Card | K9: West | L9: Standard | M9: 44525 | N9: 1249.95 | P9: Karen Hill | Q9: 8009.77 | R9: Laptop | S9: 24
A10: TRX0194 | B10: 45428 | C10: CUST006 | D10: Lisa Anderson | E10: P008 | F10: Bookshelf | G10: Furniture | H10: 2 | I10: 149.99 | J10: Credit Card | K10: West | L10: Basic | M10: 44823 | N10: 299.98 | P10: Daniel King | Q10: 7309.8 | R10: Headphones | S10: 16
A11: TRX0130 | B11: 45430 | C11: CUST002 | D11: Emma Wilson | E11: P008 | F11: Bookshelf | G11: Furniture | H11: 3 | I11: 149.99 | J11: Credit Card | K11: West | L11: Premium | M11: 45068 | N11: 449.97 | P11: Lawrence Reed | Q11: 6989.77 | R11: Office Chair | S11: 15
A12: TRX0041 | B12: 45432 | C12: CUST021 | D12: Kevin Scott | E12: P001 | F12: Laptop | G12: Electronics | H12: 1 | I12: 899.99 | J12: Credit Card | K12: West | L12: Premium | M12: 44578 | N12: 899.99 | P12: Joseph Jackson | Q12: 6949.84 | R12: Coffee Maker | S12: 14
A13: TRX0015 | B13: 45440 | C13: CUST008 | D13: Jennifer Taylor | E13: P002 | F13: Smartphone | G13: Electronics | H13: 5 | I13: 699.99 | J13: PayPal | K13: West | L13: Standard | M13: 44407 | N13: 3499.95 | P13: Helen Roberts | Q13: 6459.79 | R13: Grand Total | S13: 250
A14: TRX0128 | B14: 45444 | C14: CUST040 | D14: Sharon Butler | E14: P005 | F14: Blender | G14: Appliances | H14: 2 | I14: 59.99 | J14: Cash | K14: West | L14: Basic | M14: 45390 | N14: 119.98 | P14: Gerald Murphy | Q14: 6379.87
A15: TRX0061 | B15: 45460 | C15: CUST028 | D15: Betty Campbell | E15: P005 | F15: Blender | G15: Appliances | H15: 1 | I15: 59.99 | J15: Debit Card | K15: West | L15: Premium | M15: 45190 | N15: 59.99 | P15: Sandra Phillips | Q15: 6349.83
A16: TRX0007 | B16: 45469 | C16: CUST009 | D16: Robert Thomas | E16: P010 | F16: Keyboard | G16: Electronics | H16: 2 | I16: 89.99 | J16: Cash | K16: West | L16: Basic | M16: 44438 | N16: 179.98 | P16: Michael Brown | Q16: 6169.74
A17: TRX0192 | B17: 45475 | C17: CUST017 | D17: Charles Allen | E17: P010 | F17: Keyboard | G17: Electronics | H17: 1 | I17: 89.99 | J17: PayPal | K17: West | L17: Standard | M17: 44802 | N17: 89.99 | P17: Peter Richardson | Q17: 5949.85
A18: TRX0169 | B18: 45490 | C18: CUST047 | D18: Gerald Murphy | E18: P005 | F18: Blender | G18: Appliances | H18: 3 | I18: 59.99 | J18: Credit Card | K18: West | L18: Basic | M18: 45130 | N18: 179.97 | P18: Betty Campbell | Q18: 5649.84
A19: TRX0065 | B19: 45509 | C19: CUST016 | D19: Elizabeth Hall | E19: P008 | F19: Bookshelf | G19: Furniture | H19: 2 | I19: 149.99 | J19: Credit Card | K19: West | L19: Basic | M19: 44542 | N19: 299.98 | P19: Sharon Butler | Q19: 5619.87
A20: TRX0170 | B20: 45532 | C20: CUST034 | D20: Carol Evans | E20: P003 | F20: Headphones | G20: Electronics | H20: 3 | I20: 149.99 | J20: Cash | K20: West | L20: Premium | M20: 45212 | N20: 449.97 | P20: Harry Morgan | Q20: 5519.89
A21: TRX0099 | B21: 45537 | C21: CUST034 | D21: Carol Evans | E21: P009 | F21: Monitor | G21: Electronics | H21: 1 | I21: 249.99 | J21: Credit Card | K21: West | L21: Premium | M21: 44685 | N21: 249.99 | P21: Sarah Davis | Q21: 5499.81
A22: TRX0161 | B22: 45545 | C22: CUST017 | D22: Charles Allen | E22: P004 | F22: Coffee Maker | G22: Appliances | H22: 1 | I22: 79.99 | J22: Cash | K22: West | L22: Basic | M22: 44693 | N22: 79.99 | P22: Charles Allen | Q22: 5089.73
A23: TRX0158 | B23: 45579 | C23: CUST027 | D23: George Adams | E23: P001 | F23: Laptop | G23: Electronics | H23: 3 | I23: 899.99 | J23: PayPal | K23: West | L23: Basic | M23: 45215 | N23: 2699.97 | P23: Douglas Watson | Q23: 4829.89
A24: TRX0190 | B24: 45583 | C24: CUST039 | D24: Lawrence Reed | E24: P003 | F24: Headphones | G24: Electronics | H24: 2 | I24: 149.99 | J24: Credit Card | K24: West | L24: Basic | M24: 44916 | N24: 299.98 | P24: Virginia Sanders | Q24: 4789.79
A25: TRX0109 | B25: 45604 | C25: CUST010 | D25: Maria Garcia | E25: P008 | F25: Bookshelf | G25: Furniture | H25: 2 | I25: 149.99 | J25: Credit Card | K25: West | L25: Premium | M25: 44848 | N25: 299.98 | P25: William White | Q25: 4749.91
... A48: TRX0250 | B48: 45746 | C48: CUST026 | D48: Karen Hill | E48: P010 | F48: Keyboard | G48: Electronics | H48: 2 | I48: 89.99 | J48: Debit Card | K48: West | L48: Premium | M48: 44522 | N48: 179.98 | P48: Richard Lee | Q48: 739.93
P49: John Smith | Q49: 599.96
P50: Dennis Gray | Q50: 479.92
P51: Julie Foster | Q51: 239.96
P52: James Johnson | Q52: 179.97
P53: Grand Total | Q53: 229192.47

Sheet Scenario Summary
B2: Scenario Summary
D3: Current Values: | E3: best sales | F3: Average | G3: worst sales
E4: Created by disha chaudhari on 30-05-2026 | F4: Created by disha chaudhari on 30-05-2026 | G4: Created by disha chaudhari on 30-05-2026
B5: Changing Cells:
C6: $V$8 | D6: 4 | E6: 50 | F6: 30 | G6: 10
C7: $W$8 | D7: 350 | E7: 400 | F7: 350 | G7: 200
B8: Result Cells:
C9: $X$8 | D9: 1400 | E9: 20000 | F9: 10500 | G9: 2000
B10: Notes: Current Values column represents values of changing cells at
B11: time Scenario Summary Report was created. Changing cells for each
B12: scenario are highlighted in gray.

Sheet Visaulization
J2: Row Labels | K2: Sum of Total_Amount
A3: Row Labels | B3: Sum of Total_Amount | J3: 2024 | K3: 160444.73
A4: East | B4: 59288.39 | J4: Apr | K4: 20919.33
A5: North | B5: 50808.31 | J5: May | K5: 17039.35
A6: West | B6: 41408.68 | J6: Jun | K6: 19299.45
A7: Central | B7: 41288.34 | J7: Jul | K7: 18479.4
A8: South | B8: 36398.75 | J8: Aug | K8: 15759.43
A9: Grand Total | B9: 229192.47 | J9: Sep | K9: 12989.51
J10: Oct | K10: 20609.52
J11: Nov | K11: 12309.44
J12: Dec | K12: 23039.3
J13: 2025 | K13: 68747.74
J14: Jan | K14: 25799.15
J15: Feb | K15: 16069.38
J16: Mar | K16: 19899.38
J17: Apr | K17: 6979.83
J18: Grand Total | K18: 229192.47
J22: Row Labels | K22: Count of Quantity
A23: Row Labels | B23: Sum of Total_Amount | J23: Bookshelf | K23: 35
A24: Appliances | B24: 8338.74 | J24: Keyboard | K24: 34
A25: Electronics | B25: 171756.05 | J25: Smartphone | K25: 31
A26: Furniture | B26: 49097.68 | J26: Blender | K26: 29
A27: Grand Total | B27: 229192.47 | J27: Desk | K27: 26
J28: Monitor | K28: 26
J29: Laptop | K29: 24
J30: Headphones | K30: 16
J31: Office Chair | K31: 15
J32: Coffee Maker | K32: 14
J33: Grand Total | K33: 250
